{"title":"Toute l'actualité | Gouvernement.fr","url":"https://www.gouvernement.fr/toute-l-actualite","favicon":"https://www.gouvernement.fr/favicon.ico","elements":[{"contents":"","retrieved":1697218727334},{"contents":"","retrieved":1697218727336},{"contents":"","retrieved":1697218727336},{"contents":"","retrieved":1697218727336},{"contents":"","retrieved":1697218727337},{"contents":"","retrieved":1697218727337},{"contents":"","retrieved":1697218727337},{"contents":"","retrieved":1697218727339},{"contents":"","retrieved":1697218727340},{"contents":"","retrieved":1697218727341},{"contents":"","retrieved":1697218727343},{"contents":"","retrieved":1697218727345},{"contents":"","retrieved":1697218727347},{"contents":"","retrieved":1697218727348}]}