{"title":"Toute l'actualité | Gouvernement.fr","url":"https://www.gouvernement.fr/toute-l-actualite","favicon":"https://www.gouvernement.fr/favicon.ico","elements":[{"title":"Les 4 actus de la semaine du 18 au 24 septembre","contents":"<div class=\"fr-card fr-enlarge-link fr-card--horizontal fr-card--sm\" id=\"63433904-7d43-418d-a190-842e489f6d24\">\n            <div class=\"fr-card__body\">\n                <div class=\"fr-card__content\">\n                    <h4 class=\"fr-card__title fr-text-title--blue-france\">\n                        <a href=\"/actualite/les-4-actus-de-la-semaine-du-18-au-24-septembre\" class=\"fr-card__link\" target=\"_self\">\n                            Les 4 actus de la semaine du 18 au 24 septembre \n                        </a>\n                    </h4>\n                    <div class=\"fr-card__start\">\n                        <p class=\"fr-card__detail\">\n                             Citoyenneté\n                        </p>\n                    </div>\n                    <div class=\"fr-card__end\">\n                        <p class=\"fr-card__detail\">\n                            Publié 22/09/2023\n                        </p>\n                    </div>\n                </div>\n            </div>\n                            <div class=\"fr-card__img\">\n                    <img class=\"fr-responsive-img\" src=\"https://www.gouvernement.fr/upload/media/content/0001/07/1cf8783a25de2da66af89206ee3b500e675bfe39.png\" alt=\"Quatre actus de la semaine du 18 au 24 septembre\" data-fr-js-ratio=\"true\">\n                </div>\n                      \n        </div>","link":"https://www.gouvernement.fr/actualite/les-4-actus-de-la-semaine-du-18-au-24-septembre","retrieved":1695404326893},{"title":"Un robot humanoïde pour aider les aidants","contents":"<div class=\"fr-card fr-enlarge-link fr-card--horizontal fr-card--sm\" id=\"88047013-6655-4aa7-ad77-1c5a6b7a67bb\">\n            <div class=\"fr-card__body\">\n                <div class=\"fr-card__content\">\n                    <h4 class=\"fr-card__title fr-text-title--blue-france\">\n                        <a href=\"/actualite/un-robot-humanoide-pour-aider-les-aidants\" class=\"fr-card__link\" target=\"_self\">\n                            Un robot humanoïde pour aider les aidants \n                        </a>\n                    </h4>\n                    <div class=\"fr-card__start\">\n                        <p class=\"fr-card__detail\">\n                             Recherche &amp; Innovation\n                        </p>\n                    </div>\n                    <div class=\"fr-card__end\">\n                        <p class=\"fr-card__detail\">\n                            Publié 21/09/2023\n                        </p>\n                    </div>\n                </div>\n            </div>\n                            <div class=\"fr-card__img\">\n                    <img class=\"fr-responsive-img\" src=\"https://www.gouvernement.fr/upload/media/content/0001/07/ddaf6ab9b05b33c164b604414c1a9273c60ade68.jpg\" alt=\"Robots\" data-fr-js-ratio=\"true\">\n                </div>\n                      \n        </div>","link":"https://www.gouvernement.fr/actualite/un-robot-humanoide-pour-aider-les-aidants","retrieved":1695404326901},{"title":"Pourquoi les élections sénatoriales sont-elles importantes ?","contents":"<div class=\"fr-card fr-enlarge-link fr-card--horizontal fr-card--sm\" id=\"caf0c9d1-739e-4999-848e-a2e2bdccfe59\">\n            <div class=\"fr-card__body\">\n                <div class=\"fr-card__content\">\n                    <h4 class=\"fr-card__title fr-text-title--blue-france\">\n                        <a href=\"/actualite/pourquoi-les-elections-senatoriales-sont-elles-importantes\" class=\"fr-card__link\" target=\"_self\">\n                            Pourquoi les élections sénatoriales sont-elles importantes ? \n                        </a>\n                    </h4>\n                    <div class=\"fr-card__start\">\n                        <p class=\"fr-card__detail\">\n                             Citoyenneté\n                        </p>\n                    </div>\n                    <div class=\"fr-card__end\">\n                        <p class=\"fr-card__detail\">\n                            Publié 21/09/2023\n                        </p>\n                    </div>\n                </div>\n            </div>\n                            <div class=\"fr-card__img\">\n                    <img class=\"fr-responsive-img\" src=\"https://www.gouvernement.fr/upload/media/content/0001/07/f929f7a02e69871ce5fd2d2f799ac49d543d6577.jpg\" alt=\"\" data-fr-js-ratio=\"true\">\n                </div>\n                      \n        </div>","link":"https://www.gouvernement.fr/actualite/pourquoi-les-elections-senatoriales-sont-elles-importantes","retrieved":1695404326901},{"title":"Premier comité de l'intelligence artificielle générative","contents":"<div class=\"fr-card fr-enlarge-link fr-card--horizontal fr-card--sm\" id=\"36ff32f6-4e05-484b-af88-84c91b50a417\">\n            <div class=\"fr-card__body\">\n                <div class=\"fr-card__content\">\n                    <h4 class=\"fr-card__title fr-text-title--blue-france\">\n                        <a href=\"/actualite/elisabeth-borne-lance-le-premier-comite-de-lintelligence-artificielle\" class=\"fr-card__link\" target=\"_self\">\n                            Premier comité de l'intelligence artificielle générative \n                        </a>\n                    </h4>\n                    <div class=\"fr-card__start\">\n                        <p class=\"fr-card__detail\">\n                             Recherche &amp; Innovation\n                        </p>\n                    </div>\n                    <div class=\"fr-card__end\">\n                        <p class=\"fr-card__detail\">\n                            Publié 20/09/2023\n                        </p>\n                    </div>\n                </div>\n            </div>\n                            <div class=\"fr-card__img\">\n                    <img class=\"fr-responsive-img\" src=\"https://www.gouvernement.fr/upload/media/content/0001/07/7356b65d1016e9f9321008063580c299bc505ea0.jpg\" alt=\"La Première ministre, Élisabeth Borne, préside l'installation du comité  sur intelligence artificielle générative à Paris, le 19 septembre 2023.\" data-fr-js-ratio=\"true\">\n                </div>\n                      \n        </div>","link":"https://www.gouvernement.fr/actualite/elisabeth-borne-lance-le-premier-comite-de-lintelligence-artificielle","retrieved":1695404326902},{"title":"On a toutes une tête à travailler dans la tech","contents":"<div class=\"fr-card fr-enlarge-link fr-card--horizontal fr-card--sm\" id=\"e67c2f2b-b638-402c-8bfe-5762fbea2e74\">\n            <div class=\"fr-card__body\">\n                <div class=\"fr-card__content\">\n                    <h4 class=\"fr-card__title fr-text-title--blue-france\">\n                        <a href=\"/actualite/on-a-toutes-une-tete-a-travailler-dans-la-tech\" class=\"fr-card__link\" target=\"_self\">\n                            On a toutes une tête à travailler dans la tech \n                        </a>\n                    </h4>\n                    <div class=\"fr-card__start\">\n                        <p class=\"fr-card__detail\">\n                             Citoyenneté\n                        </p>\n                    </div>\n                    <div class=\"fr-card__end\">\n                        <p class=\"fr-card__detail\">\n                            Publié 20/09/2023\n                        </p>\n                    </div>\n                </div>\n            </div>\n                            <div class=\"fr-card__img\">\n                    <img class=\"fr-responsive-img\" src=\"https://www.gouvernement.fr/upload/media/content/0001/07/0d748bb5a0cd71889f5145406fd39565872dbd08.jpg\" alt=\"Une femme travaillant dans la « tech ».\" data-fr-js-ratio=\"true\">\n                </div>\n                      \n        </div>","link":"https://www.gouvernement.fr/actualite/on-a-toutes-une-tete-a-travailler-dans-la-tech","retrieved":1695404326902},{"title":"Mieux protéger les agents de la Fonction publique","contents":"<div class=\"fr-card fr-enlarge-link fr-card--horizontal fr-card--sm\" id=\"5135c247-efb1-4eea-88fb-6d77f0b51986\">\n            <div class=\"fr-card__body\">\n                <div class=\"fr-card__content\">\n                    <h4 class=\"fr-card__title fr-text-title--blue-france\">\n                        <a href=\"/actualite/un-plan-de-protection-pour-les-agents-publics\" class=\"fr-card__link\" target=\"_self\">\n                            Mieux protéger les agents de la Fonction publique \n                        </a>\n                    </h4>\n                    <div class=\"fr-card__start\">\n                        <p class=\"fr-card__detail\">\n                             Sécurité\n                        </p>\n                    </div>\n                    <div class=\"fr-card__end\">\n                        <p class=\"fr-card__detail\">\n                            Publié 19/09/2023\n                        </p>\n                    </div>\n                </div>\n            </div>\n                            <div class=\"fr-card__img\">\n                    <img class=\"fr-responsive-img\" src=\"https://www.gouvernement.fr/upload/media/content/0001/07/9e21d28b47d90bc66fe77867f8294f090cf347b1.jpg\" alt=\"Un homme passant devant l'accueil d'un Pôle emploi.\" data-fr-js-ratio=\"true\">\n                </div>\n                      \n        </div>","link":"https://www.gouvernement.fr/actualite/un-plan-de-protection-pour-les-agents-publics","retrieved":1695404326908},{"title":"Léa nous partage son métier de programmeuse informatique","contents":"<div class=\"fr-card fr-enlarge-link fr-card--horizontal fr-card--sm\" id=\"8c409a98-7eb7-482f-85de-7862b020d515\">\n            <div class=\"fr-card__body\">\n                <div class=\"fr-card__content\">\n                    <h4 class=\"fr-card__title fr-text-title--blue-france\">\n                        <a href=\"/actualite/la-journee-type-de-lea-programmeuse-informatique\" class=\"fr-card__link\" target=\"_self\">\n                            Léa nous partage son métier de programmeuse informatique \n                        </a>\n                    </h4>\n                    <div class=\"fr-card__start\">\n                        <p class=\"fr-card__detail\">\n                             Citoyenneté\n                        </p>\n                    </div>\n                    <div class=\"fr-card__end\">\n                        <p class=\"fr-card__detail\">\n                            Publié 18/09/2023\n                        </p>\n                    </div>\n                </div>\n            </div>\n                            <div class=\"fr-card__img\">\n                    <img class=\"fr-responsive-img\" src=\"https://www.gouvernement.fr/upload/media/content/0001/07/8f29bc8d6c1a10052de18db79eac31ae9473e567.jpg\" alt=\"Programmeuse.\" data-fr-js-ratio=\"true\">\n                </div>\n                      \n        </div>","link":"https://www.gouvernement.fr/actualite/la-journee-type-de-lea-programmeuse-informatique","retrieved":1695404326910},{"title":"Un traitement préventif contre la bronchiolite","contents":"<div class=\"fr-card fr-enlarge-link fr-card--horizontal fr-card--sm\" id=\"1ae00a01-7ef6-4f9c-96c9-b4519debc8e3\">\n            <div class=\"fr-card__body\">\n                <div class=\"fr-card__content\">\n                    <h4 class=\"fr-card__title fr-text-title--blue-france\">\n                        <a href=\"/actualite/proteger-les-nourrissons-contre-la-bronchiolite\" class=\"fr-card__link\" target=\"_self\">\n                            Un traitement préventif contre la bronchiolite \n                        </a>\n                    </h4>\n                    <div class=\"fr-card__start\">\n                        <p class=\"fr-card__detail\">\n                             Santé\n                        </p>\n                    </div>\n                    <div class=\"fr-card__end\">\n                        <p class=\"fr-card__detail\">\n                            Publié 18/09/2023\n                        </p>\n                    </div>\n                </div>\n            </div>\n                            <div class=\"fr-card__img\">\n                    <img class=\"fr-responsive-img\" src=\"https://www.gouvernement.fr/upload/media/content/0001/07/5025a6ff6a9f0d8f08e756914cd52386460f4a25.jpg\" alt=\"Une maman prenant soin de son bébé.\" data-fr-js-ratio=\"true\">\n                </div>\n                      \n        </div>","link":"https://www.gouvernement.fr/actualite/proteger-les-nourrissons-contre-la-bronchiolite","retrieved":1695404326912},{"title":"À la découverte du patrimoine de la République","contents":"<div class=\"fr-card fr-enlarge-link fr-card--horizontal fr-card--sm\" id=\"47e28b1d-c7cc-445a-9ab3-385a49b3f310\">\n            <div class=\"fr-card__body\">\n                <div class=\"fr-card__content\">\n                    <h4 class=\"fr-card__title fr-text-title--blue-france\">\n                        <a href=\"/actualite/a-la-decouverte-du-patrimoine-de-la-republique\" class=\"fr-card__link\" target=\"_self\">\n                            À la découverte du patrimoine de la République \n                        </a>\n                    </h4>\n                    <div class=\"fr-card__start\">\n                        <p class=\"fr-card__detail\">\n                             Culture\n                        </p>\n                    </div>\n                    <div class=\"fr-card__end\">\n                        <p class=\"fr-card__detail\">\n                            Publié 15/09/2023\n                        </p>\n                    </div>\n                </div>\n            </div>\n                            <div class=\"fr-card__img\">\n                    <img class=\"fr-responsive-img\" src=\"https://www.gouvernement.fr/upload/media/content/0001/07/25d1b6d3056985c2f683f4521b4f4993d9c6f62c.jpg\" alt=\"JEP 2023\" data-fr-js-ratio=\"true\">\n                </div>\n                      \n        </div>","link":"https://www.gouvernement.fr/actualite/a-la-decouverte-du-patrimoine-de-la-republique","retrieved":1695404326913},{"title":"Les 4 actus de la semaine du 11 au 17 septembre","contents":"<div class=\"fr-card fr-enlarge-link fr-card--horizontal fr-card--sm\" id=\"28133c9d-53f5-49a5-a7ab-1aaaab21b39f\">\n            <div class=\"fr-card__body\">\n                <div class=\"fr-card__content\">\n                    <h4 class=\"fr-card__title fr-text-title--blue-france\">\n                        <a href=\"/actualite/les-4-actus-de-la-semaine-du-11-au-17-septembre\" class=\"fr-card__link\" target=\"_self\">\n                            Les 4 actus de la semaine du 11 au 17 septembre \n                        </a>\n                    </h4>\n                    <div class=\"fr-card__start\">\n                        <p class=\"fr-card__detail\">\n                             Citoyenneté\n                        </p>\n                    </div>\n                    <div class=\"fr-card__end\">\n                        <p class=\"fr-card__detail\">\n                            Publié 15/09/2023\n                        </p>\n                    </div>\n                </div>\n            </div>\n                            <div class=\"fr-card__img\">\n                    <img class=\"fr-responsive-img\" src=\"https://www.gouvernement.fr/upload/media/content/0001/07/dfc73b94ab627adea43c49b4abd11d671fc530b8.png\" alt=\"4 actus de la semaine du 11 - 17 septembre 2023\" data-fr-js-ratio=\"true\">\n                </div>\n                      \n        </div>","link":"https://www.gouvernement.fr/actualite/les-4-actus-de-la-semaine-du-11-au-17-septembre","retrieved":1695404326915},{"title":"La petite histoire de la devise « Liberté, Égalité, Fraternité »","contents":"<div class=\"fr-card fr-enlarge-link fr-card--horizontal fr-card--sm\" id=\"c3755624-5e6b-4007-9e8c-0058ee14a7b8\">\n            <div class=\"fr-card__body\">\n                <div class=\"fr-card__content\">\n                    <h4 class=\"fr-card__title fr-text-title--blue-france\">\n                        <a href=\"/actualite/la-petite-histoire-de-la-devise-francaise-liberte-egalite-fraternite\" class=\"fr-card__link\" target=\"_self\">\n                            La petite histoire de la devise « Liberté, Égalité, Fraternité » \n                        </a>\n                    </h4>\n                    <div class=\"fr-card__start\">\n                        <p class=\"fr-card__detail\">\n                             Culture\n                        </p>\n                    </div>\n                    <div class=\"fr-card__end\">\n                        <p class=\"fr-card__detail\">\n                            Publié 15/09/2023\n                        </p>\n                    </div>\n                </div>\n            </div>\n                            <div class=\"fr-card__img\">\n                    <img class=\"fr-responsive-img\" src=\"https://www.gouvernement.fr/upload/media/content/0001/07/5a24390df30918a6d4d02f1b085ec598811873a2.png\" alt=\"Bandeau de la devise républicaine.\" data-fr-js-ratio=\"true\">\n                </div>\n                      \n        </div>","link":"https://www.gouvernement.fr/actualite/la-petite-histoire-de-la-devise-francaise-liberte-egalite-fraternite","retrieved":1695404326916},{"title":"Une campagne contre les violences sexuelles faites aux enfants","contents":"<div class=\"fr-card fr-enlarge-link fr-card--horizontal fr-card--sm\" id=\"e54ef611-f239-4c52-846a-6dff811fc897\">\n            <div class=\"fr-card__body\">\n                <div class=\"fr-card__content\">\n                    <h4 class=\"fr-card__title fr-text-title--blue-france\">\n                        <a href=\"/actualite/le-gouvernement-contre-les-violences-sexuelles-faites-aux-enfants\" class=\"fr-card__link\" target=\"_self\">\n                            Une campagne contre les violences sexuelles faites aux enfants \n                        </a>\n                    </h4>\n                    <div class=\"fr-card__start\">\n                        <p class=\"fr-card__detail\">\n                             Affaires sociales\n                        </p>\n                    </div>\n                    <div class=\"fr-card__end\">\n                        <p class=\"fr-card__detail\">\n                            Publié 14/09/2023\n                        </p>\n                    </div>\n                </div>\n            </div>\n                            <div class=\"fr-card__img\">\n                    <img class=\"fr-responsive-img\" src=\"https://www.gouvernement.fr/upload/media/content/0001/07/ab52fdd746e6df753d6adb779c2762a364b7eb77.jpg\" alt=\"Une petite fille.\" data-fr-js-ratio=\"true\">\n                </div>\n                      \n        </div>","link":"https://www.gouvernement.fr/actualite/le-gouvernement-contre-les-violences-sexuelles-faites-aux-enfants","retrieved":1695404326925},{"title":"Alléger la charge de travail grâce au  « cobot »","contents":"<div class=\"fr-card fr-enlarge-link fr-card--horizontal fr-card--sm\" id=\"3c926f71-714a-4111-a493-4108feb274e7\">\n            <div class=\"fr-card__body\">\n                <div class=\"fr-card__content\">\n                    <h4 class=\"fr-card__title fr-text-title--blue-france\">\n                        <a href=\"/actualite/alleger-la-charge-de-travail-grace-au-cobot\" class=\"fr-card__link\" target=\"_self\">\n                            Alléger la charge de travail grâce au  « cobot » \n                        </a>\n                    </h4>\n                    <div class=\"fr-card__start\">\n                        <p class=\"fr-card__detail\">\n                             Économie\n                        </p>\n                    </div>\n                    <div class=\"fr-card__end\">\n                        <p class=\"fr-card__detail\">\n                            Publié 13/09/2023\n                        </p>\n                    </div>\n                </div>\n            </div>\n                            <div class=\"fr-card__img\">\n                    <img class=\"fr-responsive-img\" src=\"https://www.gouvernement.fr/upload/media/content/0001/07/a8f27c6a2329572e14c2e246ae1c8a38b9c184ca.png\" alt=\"Théo Rougemont, directeur opérationnel de MS-Innov.\" data-fr-js-ratio=\"true\">\n                </div>\n                      \n        </div>","link":"https://www.gouvernement.fr/actualite/alleger-la-charge-de-travail-grace-au-cobot","retrieved":1695404326926},{"title":"Un camion qui conduit à l'enseignement agricole","contents":"<div class=\"fr-card fr-enlarge-link fr-card--horizontal fr-card--sm\" id=\"95462b77-d853-45ab-b035-b7baeb2cd642\">\n            <div class=\"fr-card__body\">\n                <div class=\"fr-card__content\">\n                    <h4 class=\"fr-card__title fr-text-title--blue-france\">\n                        <a href=\"/actualite/un-camion-qui-conduit-a-lenseignement-agricole\" class=\"fr-card__link\" target=\"_self\">\n                            Un camion qui conduit à l'enseignement agricole \n                        </a>\n                    </h4>\n                    <div class=\"fr-card__start\">\n                        <p class=\"fr-card__detail\">\n                             Éducation\n                        </p>\n                    </div>\n                    <div class=\"fr-card__end\">\n                        <p class=\"fr-card__detail\">\n                            Publié 13/09/2023\n                        </p>\n                    </div>\n                </div>\n            </div>\n                            <div class=\"fr-card__img\">\n                    <img class=\"fr-responsive-img\" src=\"https://www.gouvernement.fr/upload/media/content/0001/07/abe43331c4558f5e8b26d48f063cc3feea1f22f1.jpg\" alt=\"Camion « l'aventure du vivant »\" data-fr-js-ratio=\"true\">\n                </div>\n                      \n        </div>","link":"https://www.gouvernement.fr/actualite/un-camion-qui-conduit-a-lenseignement-agricole","retrieved":1695404326928}]}